gloxonoauth/__init__.py
gloxonoauth/client.py
gloxon_oauth-0.1.0.dist-info/LICENSE
gloxon_oauth-0.1.0.dist-info/METADATA
gloxon_oauth-0.1.0.dist-info/WHEEL
gloxon_oauth-0.1.0.dist-info/top_level.txt
gloxon_oauth-0.1.0.dist-info/RECORD
